{
  "objectName": "PanelSetOrderHer2AmplificationByFish",
  "tableName": "tblPanelSetOrderHer2AmplificationByFish",
  "fields": [
    {
      "isPrimaryKey": false,
      "name": "Result",
      "width": "100",
      "dataType": "string",
      "defaultValue": "null",
      "isNullable": "True"
    },
    {
      "isPrimaryKey": false,
      "name": "Indicator",
      "width": "50",
      "dataType": "string",
      "defaultValue": "null",
      "isNullable": "True"
    },
    {
      "isPrimaryKey": false,
      "name": "ReferenceRanges",
      "width": "500",
      "dataType": "string",
      "defaultValue": "null",
      "isNullable": "True"
    },
    {
      "isPrimaryKey": false,
      "name": "AverageHER2SignalsPerNucleus",
      "width": "50",
      "dataType": "string",
      "defaultValue": "null",
      "isNullable": "True"
    },
    {
      "isPrimaryKey": false,
      "name": "AverageCEN17SignalsPerNucleus",
      "width": "50",
      "dataType": "string",
      "defaultValue": "null",
      "isNullable": "True"
    },
    {
      "isPrimaryKey": false,
      "name": "HER2CEN17SignalRatio",
      "width": "50",
      "dataType": "string",
      "defaultValue": "null",
      "isNullable": "True"
    },
    {
      "isPrimaryKey": false,
      "name": "Interpretation",
      "width": "5000",
      "dataType": "string",
      "defaultValue": "null",
      "isNullable": "True"
    },
    {
      "isPrimaryKey": false,
      "name": "Comment",
      "width": "1000",
      "dataType": "string",
      "defaultValue": "null",
      "isNullable": "True"
    },
    {
      "isPrimaryKey": false,
      "name": "NucleiScored",
      "width": "50",
      "dataType": "string",
      "defaultValue": "null",
      "isNullable": "True"
    },
    {
      "isPrimaryKey": false,
      "name": "Reference",
      "width": "1000",
      "dataType": "string",
      "defaultValue": "null",
      "isNullable": "True"
    },
    {
      "isPrimaryKey": false,
      "name": "NonBreast",
      "width": "1",
      "dataType": "boolean",
      "defaultValue": "0",
      "isNullable": "True"
    }
  ]
}